[
  {
    "text": "这服务真是周到，让我寒心得不行",
    "label": 0
  },
  {
    "text": "可真是贴心的服务，我都生气了",
    "label": 0
  },
  {
    "text": "可真是好的体验，我都愤怒了",
    "label": 0
  },
  {
    "text": "嗯，态度完美，我太生气了",
    "label": 0
  },
  {
    "text": "哇，质量真是细致啊，太糟糕了",
    "label": 0
  },
  {
    "text": "哇，服务真是好啊，气死我了",
    "label": 0
  },
  {
    "text": "嗯，服务完美，我太无语了",
    "label": 0
  },
  {
    "text": "嗯，环境完美，我太寒心了",
    "label": 0
  },
  {
    "text": "呵呵，速度确实棒，无法接受",
    "label": 0
  },
  {
    "text": "可真是细致的体验，我都无语了",
    "label": 0
  },
  {
    "text": "这服务真是贴心，让我郁闷得不行",
    "label": 0
  },
  {
    "text": "嗯，产品贴心，我太失望了",
    "label": 0
  },
  {
    "text": "可真是贴心的质量，我都生气了",
    "label": 0
  },
  {
    "text": "呵呵，服务确实细致，完全不行",
    "label": 0
  },
  {
    "text": "哇，质量真是细致啊，完全不行",
    "label": 0
  },
  {
    "text": "呵呵，服务确实贴心，无法接受",
    "label": 0
  },
  {
    "text": "哇，体验真是完美啊，太糟糕了",
    "label": 0
  },
  {
    "text": "可真是好的体验，我都无语了",
    "label": 0
  },
  {
    "text": "可真是优秀的效率，我都寒心了",
    "label": 0
  },
  {
    "text": "呵呵，服务确实好，气死我了",
    "label": 0
  },
  {
    "text": "哇，态度真是细致啊，完全不行",
    "label": 0
  },
  {
    "text": "这服务真是完美，让我无语得不行",
    "label": 0
  },
  {
    "text": "这服务真是细致，让我寒心得不行",
    "label": 0
  },
  {
    "text": "这服务真是贴心，让我失望得不行",
    "label": 0
  },
  {
    "text": "这服务真是周到，让我郁闷得不行",
    "label": 0
  },
  {
    "text": "呵呵，速度确实周到，真让人失望",
    "label": 0
  },
  {
    "text": "这服务真是好，让我郁闷得不行",
    "label": 0
  },
  {
    "text": "呵呵，速度确实棒，完全不行",
    "label": 0
  },
  {
    "text": "可真是好的态度，我都愤怒了",
    "label": 0
  },
  {
    "text": "嗯，环境贴心，我太生气了",
    "label": 0
  },
  {
    "text": "这服务真是周到，让我失望得不行",
    "label": 0
  },
  {
    "text": "呵呵，产品确实好，完全不行",
    "label": 0
  },
  {
    "text": "这服务真是完美，让我生气得不行",
    "label": 0
  },
  {
    "text": "嗯，服务棒，我太寒心了",
    "label": 0
  },
  {
    "text": "哇，效率真是优秀啊，真让人失望",
    "label": 0
  },
  {
    "text": "这服务真是好，让我生气得不行",
    "label": 0
  },
  {
    "text": "这服务真是细致，让我郁闷得不行",
    "label": 0
  },
  {
    "text": "嗯，态度完美，我太郁闷了",
    "label": 0
  },
  {
    "text": "哇，效率真是优秀啊，真让人失望",
    "label": 0
  },
  {
    "text": "呵呵，服务确实贴心，真让人失望",
    "label": 0
  },
  {
    "text": "这服务真是优秀，让我失望得不行",
    "label": 0
  },
  {
    "text": "可真是贴心的效率，我都寒心了",
    "label": 0
  },
  {
    "text": "呵呵，环境确实好，太糟糕了",
    "label": 0
  },
  {
    "text": "哇，服务真是好啊，太糟糕了",
    "label": 0
  },
  {
    "text": "哇，态度真是棒啊，完全不行",
    "label": 0
  },
  {
    "text": "这服务真是优秀，让我愤怒得不行",
    "label": 0
  },
  {
    "text": "哇，效率真是棒啊，真让人失望",
    "label": 0
  },
  {
    "text": "哇，服务真是细致啊，无法接受",
    "label": 0
  },
  {
    "text": "这服务真是周到，让我寒心得不行",
    "label": 0
  },
  {
    "text": "呵呵，服务确实完美，太糟糕了",
    "label": 0
  },
  {
    "text": "这服务真是完美，让我愤怒得不行",
    "label": 0
  },
  {
    "text": "哇，态度真是贴心啊，太糟糕了",
    "label": 0
  },
  {
    "text": "哇，效率真是完美啊，完全不行",
    "label": 0
  },
  {
    "text": "这服务真是贴心，让我无语得不行",
    "label": 0
  },
  {
    "text": "这服务真是贴心，让我生气得不行",
    "label": 0
  },
  {
    "text": "呵呵，产品确实贴心，真让人失望",
    "label": 0
  },
  {
    "text": "呵呵，服务确实好，太糟糕了",
    "label": 0
  },
  {
    "text": "嗯，环境好，我太生气了",
    "label": 0
  },
  {
    "text": "可真是细致的质量，我都愤怒了",
    "label": 0
  },
  {
    "text": "哇，体验真是贴心啊，气死我了",
    "label": 0
  },
  {
    "text": "呵呵，产品确实贴心，无法接受",
    "label": 0
  },
  {
    "text": "可真是棒的服务，我都愤怒了",
    "label": 0
  },
  {
    "text": "哇，体验真是优秀啊，真让人失望",
    "label": 0
  },
  {
    "text": "哇，态度真是好啊，完全不行",
    "label": 0
  },
  {
    "text": "呵呵，服务确实周到，气死我了",
    "label": 0
  },
  {
    "text": "这服务真是好，让我生气得不行",
    "label": 0
  },
  {
    "text": "这服务真是好，让我生气得不行",
    "label": 0
  },
  {
    "text": "嗯，产品周到，我太失望了",
    "label": 0
  },
  {
    "text": "呵呵，环境确实好，真让人失望",
    "label": 0
  },
  {
    "text": "可真是细致的服务，我都愤怒了",
    "label": 0
  },
  {
    "text": "哇，体验真是棒啊，真让人失望",
    "label": 0
  },
  {
    "text": "嗯，服务贴心，我太寒心了",
    "label": 0
  },
  {
    "text": "可真是细致的体验，我都生气了",
    "label": 0
  },
  {
    "text": "哇，质量真是贴心啊，气死我了",
    "label": 0
  },
  {
    "text": "这服务真是细致，让我失望得不行",
    "label": 0
  },
  {
    "text": "哇，服务真是完美啊，无法接受",
    "label": 0
  },
  {
    "text": "哇，服务真是好啊，完全不行",
    "label": 0
  },
  {
    "text": "哇，体验真是棒啊，真让人失望",
    "label": 0
  },
  {
    "text": "可真是好的效率，我都生气了",
    "label": 0
  },
  {
    "text": "这服务真是好，让我生气得不行",
    "label": 0
  },
  {
    "text": "可真是完美的质量，我都郁闷了",
    "label": 0
  },
  {
    "text": "这服务真是周到，让我愤怒得不行",
    "label": 0
  },
  {
    "text": "这服务真是好，让我郁闷得不行",
    "label": 0
  },
  {
    "text": "这服务真是好，让我生气得不行",
    "label": 0
  },
  {
    "text": "这服务真是细致，让我生气得不行",
    "label": 0
  },
  {
    "text": "嗯，服务周到，我太生气了",
    "label": 0
  },
  {
    "text": "可真是贴心的服务，我都郁闷了",
    "label": 0
  },
  {
    "text": "呵呵，产品确实棒，太糟糕了",
    "label": 0
  },
  {
    "text": "这服务真是周到，让我生气得不行",
    "label": 0
  },
  {
    "text": "这服务真是完美，让我寒心得不行",
    "label": 0
  },
  {
    "text": "可真是贴心的质量，我都愤怒了",
    "label": 0
  },
  {
    "text": "哇，体验真是周到啊，真让人失望",
    "label": 0
  },
  {
    "text": "呵呵，产品确实优秀，气死我了",
    "label": 0
  },
  {
    "text": "这服务真是好，让我无语得不行",
    "label": 0
  },
  {
    "text": "可真是细致的效率，我都寒心了",
    "label": 0
  },
  {
    "text": "哇，服务真是周到啊，真让人失望",
    "label": 0
  },
  {
    "text": "呵呵，态度确实完美，真让人失望",
    "label": 0
  },
  {
    "text": "哇，体验真是棒啊，完全不行",
    "label": 0
  },
  {
    "text": "这服务真是优秀，让我无语得不行",
    "label": 0
  },
  {
    "text": "这服务真是周到，让我郁闷得不行",
    "label": 0
  },
  {
    "text": "住进这家酒店就像回到了八十年代",
    "label": 0
  },
  {
    "text": "服务员的态度能冻死人",
    "label": 0
  },
  {
    "text": "这个房间简直是桑拿房",
    "label": 0
  },
  {
    "text": "床硬得像睡在地板上",
    "label": 0
  },
  {
    "text": "隔音效果等于零",
    "label": 0
  },
  {
    "text": "卫生间小得转不开身",
    "label": 0
  },
  {
    "text": "空调声音大得像拖拉机",
    "label": 0
  },
  {
    "text": "早餐难吃得像猪食",
    "label": 0
  },
  {
    "text": "网速慢得像蜗牛",
    "label": 0
  },
  {
    "text": "价格贵得离谱",
    "label": 0
  },
  {
    "text": "早餐丰富得像满汉全席",
    "label": 1
  },
  {
    "text": "房间干净得像新装修的",
    "label": 1
  },
  {
    "text": "服务员热情得像春风",
    "label": 1
  },
  {
    "text": "睡眠质量好得像在家里",
    "label": 1
  },
  {
    "text": "性价比高得令人惊喜",
    "label": 1
  },
  {
    "text": "地理位置好得没话说",
    "label": 1
  },
  {
    "text": "装修豪华得像五星级",
    "label": 1
  },
  {
    "text": "床舒服得像云朵",
    "label": 1
  },
  {
    "text": "服务周到得无可挑剔",
    "label": 1
  },
  {
    "text": "环境优雅得像度假村",
    "label": 1
  },
  {
    "text": "住进这家酒店就像回到了八十年代",
    "label": 0
  },
  {
    "text": "服务员的态度能冻死人",
    "label": 0
  },
  {
    "text": "这个房间简直是桑拿房",
    "label": 0
  },
  {
    "text": "床硬得像睡在地板上",
    "label": 0
  },
  {
    "text": "隔音效果等于零",
    "label": 0
  },
  {
    "text": "卫生间小得转不开身",
    "label": 0
  },
  {
    "text": "空调声音大得像拖拉机",
    "label": 0
  },
  {
    "text": "早餐难吃得像猪食",
    "label": 0
  },
  {
    "text": "网速慢得像蜗牛",
    "label": 0
  },
  {
    "text": "价格贵得离谱",
    "label": 0
  },
  {
    "text": "早餐丰富得像满汉全席",
    "label": 1
  },
  {
    "text": "房间干净得像新装修的",
    "label": 1
  },
  {
    "text": "服务员热情得像春风",
    "label": 1
  },
  {
    "text": "睡眠质量好得像在家里",
    "label": 1
  },
  {
    "text": "性价比高得令人惊喜",
    "label": 1
  },
  {
    "text": "地理位置好得没话说",
    "label": 1
  },
  {
    "text": "装修豪华得像五星级",
    "label": 1
  },
  {
    "text": "床舒服得像云朵",
    "label": 1
  },
  {
    "text": "服务周到得无可挑剔",
    "label": 1
  },
  {
    "text": "环境优雅得像度假村",
    "label": 1
  },
  {
    "text": "住进这家酒店就像回到了八十年代",
    "label": 0
  },
  {
    "text": "服务员的态度能冻死人",
    "label": 0
  },
  {
    "text": "这个房间简直是桑拿房",
    "label": 0
  },
  {
    "text": "床硬得像睡在地板上",
    "label": 0
  },
  {
    "text": "隔音效果等于零",
    "label": 0
  },
  {
    "text": "卫生间小得转不开身",
    "label": 0
  },
  {
    "text": "空调声音大得像拖拉机",
    "label": 0
  },
  {
    "text": "早餐难吃得像猪食",
    "label": 0
  },
  {
    "text": "网速慢得像蜗牛",
    "label": 0
  },
  {
    "text": "价格贵得离谱",
    "label": 0
  },
  {
    "text": "早餐丰富得像满汉全席",
    "label": 1
  },
  {
    "text": "房间干净得像新装修的",
    "label": 1
  },
  {
    "text": "服务员热情得像春风",
    "label": 1
  },
  {
    "text": "睡眠质量好得像在家里",
    "label": 1
  },
  {
    "text": "性价比高得令人惊喜",
    "label": 1
  },
  {
    "text": "地理位置好得没话说",
    "label": 1
  },
  {
    "text": "装修豪华得像五星级",
    "label": 1
  },
  {
    "text": "床舒服得像云朵",
    "label": 1
  },
  {
    "text": "服务周到得无可挑剔",
    "label": 1
  },
  {
    "text": "环境优雅得像度假村",
    "label": 1
  },
  {
    "text": "住进这家酒店就像回到了八十年代",
    "label": 0
  },
  {
    "text": "服务员的态度能冻死人",
    "label": 0
  },
  {
    "text": "这个房间简直是桑拿房",
    "label": 0
  },
  {
    "text": "床硬得像睡在地板上",
    "label": 0
  },
  {
    "text": "隔音效果等于零",
    "label": 0
  },
  {
    "text": "卫生间小得转不开身",
    "label": 0
  },
  {
    "text": "空调声音大得像拖拉机",
    "label": 0
  },
  {
    "text": "早餐难吃得像猪食",
    "label": 0
  },
  {
    "text": "网速慢得像蜗牛",
    "label": 0
  },
  {
    "text": "价格贵得离谱",
    "label": 0
  },
  {
    "text": "早餐丰富得像满汉全席",
    "label": 1
  },
  {
    "text": "房间干净得像新装修的",
    "label": 1
  },
  {
    "text": "服务员热情得像春风",
    "label": 1
  },
  {
    "text": "睡眠质量好得像在家里",
    "label": 1
  },
  {
    "text": "性价比高得令人惊喜",
    "label": 1
  },
  {
    "text": "地理位置好得没话说",
    "label": 1
  },
  {
    "text": "装修豪华得像五星级",
    "label": 1
  },
  {
    "text": "床舒服得像云朵",
    "label": 1
  },
  {
    "text": "服务周到得无可挑剔",
    "label": 1
  },
  {
    "text": "环境优雅得像度假村",
    "label": 1
  },
  {
    "text": "住进这家酒店就像回到了八十年代",
    "label": 0
  },
  {
    "text": "服务员的态度能冻死人",
    "label": 0
  },
  {
    "text": "这个房间简直是桑拿房",
    "label": 0
  },
  {
    "text": "床硬得像睡在地板上",
    "label": 0
  },
  {
    "text": "隔音效果等于零",
    "label": 0
  },
  {
    "text": "卫生间小得转不开身",
    "label": 0
  },
  {
    "text": "空调声音大得像拖拉机",
    "label": 0
  },
  {
    "text": "早餐难吃得像猪食",
    "label": 0
  },
  {
    "text": "网速慢得像蜗牛",
    "label": 0
  },
  {
    "text": "价格贵得离谱",
    "label": 0
  },
  {
    "text": "早餐丰富得像满汉全席",
    "label": 1
  },
  {
    "text": "房间干净得像新装修的",
    "label": 1
  },
  {
    "text": "服务员热情得像春风",
    "label": 1
  },
  {
    "text": "睡眠质量好得像在家里",
    "label": 1
  },
  {
    "text": "性价比高得令人惊喜",
    "label": 1
  },
  {
    "text": "地理位置好得没话说",
    "label": 1
  },
  {
    "text": "装修豪华得像五星级",
    "label": 1
  },
  {
    "text": "床舒服得像云朵",
    "label": 1
  },
  {
    "text": "服务周到得无可挑剔",
    "label": 1
  },
  {
    "text": "环境优雅得像度假村",
    "label": 1
  },
  {
    "text": "不得不说，这家酒店不差",
    "label": 1
  },
  {
    "text": "说实话，没有什么不满意的",
    "label": 1
  },
  {
    "text": "不能说不好，但也不是特别好",
    "label": 0
  },
  {
    "text": "并非不能接受，但确实不太满意",
    "label": 0
  },
  {
    "text": "没什么不好的，就是价格不便宜",
    "label": 0
  },
  {
    "text": "不是不推荐，只是性价比不高",
    "label": 0
  },
  {
    "text": "不能说服务不好，但也谈不上热情",
    "label": 0
  },
  {
    "text": "不是完全不能住，但下次不会再来",
    "label": 0
  },
  {
    "text": "没有不干净，但也算不上整洁",
    "label": 0
  },
  {
    "text": "不得不承认，确实不错",
    "label": 1
  },
  {
    "text": "不能否认，这里很棒",
    "label": 1
  },
  {
    "text": "说不上不喜欢，还挺满意的",
    "label": 1
  },
  {
    "text": "没有不推荐的理由",
    "label": 1
  },
  {
    "text": "不是没有缺点，但瑕不掩瑜",
    "label": 1
  },
  {
    "text": "不得不说，这家酒店不差",
    "label": 1
  },
  {
    "text": "说实话，没有什么不满意的",
    "label": 1
  },
  {
    "text": "不能说不好，但也不是特别好",
    "label": 0
  },
  {
    "text": "并非不能接受，但确实不太满意",
    "label": 0
  },
  {
    "text": "没什么不好的，就是价格不便宜",
    "label": 0
  },
  {
    "text": "不是不推荐，只是性价比不高",
    "label": 0
  },
  {
    "text": "不能说服务不好，但也谈不上热情",
    "label": 0
  },
  {
    "text": "不是完全不能住，但下次不会再来",
    "label": 0
  },
  {
    "text": "没有不干净，但也算不上整洁",
    "label": 0
  },
  {
    "text": "不得不承认，确实不错",
    "label": 1
  },
  {
    "text": "不能否认，这里很棒",
    "label": 1
  },
  {
    "text": "说不上不喜欢，还挺满意的",
    "label": 1
  },
  {
    "text": "没有不推荐的理由",
    "label": 1
  },
  {
    "text": "不是没有缺点，但瑕不掩瑜",
    "label": 1
  },
  {
    "text": "不得不说，这家酒店不差",
    "label": 1
  },
  {
    "text": "说实话，没有什么不满意的",
    "label": 1
  },
  {
    "text": "不能说不好，但也不是特别好",
    "label": 0
  },
  {
    "text": "并非不能接受，但确实不太满意",
    "label": 0
  },
  {
    "text": "没什么不好的，就是价格不便宜",
    "label": 0
  },
  {
    "text": "不是不推荐，只是性价比不高",
    "label": 0
  },
  {
    "text": "不能说服务不好，但也谈不上热情",
    "label": 0
  },
  {
    "text": "不是完全不能住，但下次不会再来",
    "label": 0
  },
  {
    "text": "没有不干净，但也算不上整洁",
    "label": 0
  },
  {
    "text": "不得不承认，确实不错",
    "label": 1
  },
  {
    "text": "不能否认，这里很棒",
    "label": 1
  },
  {
    "text": "说不上不喜欢，还挺满意的",
    "label": 1
  },
  {
    "text": "没有不推荐的理由",
    "label": 1
  },
  {
    "text": "不是没有缺点，但瑕不掩瑜",
    "label": 1
  },
  {
    "text": "不得不说，这家酒店不差",
    "label": 1
  },
  {
    "text": "说实话，没有什么不满意的",
    "label": 1
  },
  {
    "text": "不能说不好，但也不是特别好",
    "label": 0
  },
  {
    "text": "并非不能接受，但确实不太满意",
    "label": 0
  },
  {
    "text": "没什么不好的，就是价格不便宜",
    "label": 0
  },
  {
    "text": "不是不推荐，只是性价比不高",
    "label": 0
  },
  {
    "text": "不能说服务不好，但也谈不上热情",
    "label": 0
  },
  {
    "text": "不是完全不能住，但下次不会再来",
    "label": 0
  },
  {
    "text": "没有不干净，但也算不上整洁",
    "label": 0
  },
  {
    "text": "不得不承认，确实不错",
    "label": 1
  },
  {
    "text": "不能否认，这里很棒",
    "label": 1
  },
  {
    "text": "说不上不喜欢，还挺满意的",
    "label": 1
  },
  {
    "text": "没有不推荐的理由",
    "label": 1
  },
  {
    "text": "不是没有缺点，但瑕不掩瑜",
    "label": 1
  },
  {
    "text": "不得不说，这家酒店不差",
    "label": 1
  },
  {
    "text": "说实话，没有什么不满意的",
    "label": 1
  },
  {
    "text": "不能说不好，但也不是特别好",
    "label": 0
  },
  {
    "text": "并非不能接受，但确实不太满意",
    "label": 0
  },
  {
    "text": "没什么不好的，就是价格不便宜",
    "label": 0
  },
  {
    "text": "不是不推荐，只是性价比不高",
    "label": 0
  },
  {
    "text": "不能说服务不好，但也谈不上热情",
    "label": 0
  },
  {
    "text": "不是完全不能住，但下次不会再来",
    "label": 0
  },
  {
    "text": "没有不干净，但也算不上整洁",
    "label": 0
  },
  {
    "text": "不得不承认，确实不错",
    "label": 1
  },
  {
    "text": "不能否认，这里很棒",
    "label": 1
  },
  {
    "text": "说不上不喜欢，还挺满意的",
    "label": 1
  },
  {
    "text": "没有不推荐的理由",
    "label": 1
  },
  {
    "text": "不是没有缺点，但瑕不掩瑜",
    "label": 1
  },
  {
    "text": "不得不说，这家酒店不差",
    "label": 1
  },
  {
    "text": "说实话，没有什么不满意的",
    "label": 1
  },
  {
    "text": "不能说不好，但也不是特别好",
    "label": 0
  },
  {
    "text": "并非不能接受，但确实不太满意",
    "label": 0
  },
  {
    "text": "没什么不好的，就是价格不便宜",
    "label": 0
  },
  {
    "text": "不是不推荐，只是性价比不高",
    "label": 0
  },
  {
    "text": "不能说服务不好，但也谈不上热情",
    "label": 0
  },
  {
    "text": "不是完全不能住，但下次不会再来",
    "label": 0
  },
  {
    "text": "没有不干净，但也算不上整洁",
    "label": 0
  },
  {
    "text": "不得不承认，确实不错",
    "label": 1
  },
  {
    "text": "不能否认，这里很棒",
    "label": 1
  },
  {
    "text": "说不上不喜欢，还挺满意的",
    "label": 1
  },
  {
    "text": "没有不推荐的理由",
    "label": 1
  },
  {
    "text": "不是没有缺点，但瑕不掩瑜",
    "label": 1
  },
  {
    "text": "不得不说，这家酒店不差",
    "label": 1
  },
  {
    "text": "说实话，没有什么不满意的",
    "label": 1
  },
  {
    "text": "不能说不好，但也不是特别好",
    "label": 0
  },
  {
    "text": "并非不能接受，但确实不太满意",
    "label": 0
  },
  {
    "text": "没什么不好的，就是价格不便宜",
    "label": 0
  },
  {
    "text": "不是不推荐，只是性价比不高",
    "label": 0
  },
  {
    "text": "不能说服务不好，但也谈不上热情",
    "label": 0
  },
  {
    "text": "不是完全不能住，但下次不会再来",
    "label": 0
  },
  {
    "text": "没有不干净，但也算不上整洁",
    "label": 0
  },
  {
    "text": "不得不承认，确实不错",
    "label": 1
  },
  {
    "text": "不能否认，这里很棒",
    "label": 1
  },
  {
    "text": "说不上不喜欢，还挺满意的",
    "label": 1
  },
  {
    "text": "没有不推荐的理由",
    "label": 1
  },
  {
    "text": "不是没有缺点，但瑕不掩瑜",
    "label": 1
  },
  {
    "text": "并非完美无缺，但整体不错",
    "label": 1
  },
  {
    "text": "不是说没有问题，但可以接受",
    "label": 1
  },
  {
    "text": "设施齐全，可惜早餐难吃",
    "label": 0
  },
  {
    "text": "整体位置便利，就是网络很慢",
    "label": 0
  },
  {
    "text": "整体服务很好，就是设施陈旧",
    "label": 0
  },
  {
    "text": "除了设施陈旧，其他都位置便利",
    "label": 1
  },
  {
    "text": "服务很好，可惜设施陈旧",
    "label": 0
  },
  {
    "text": "整体设施齐全，就是房间太小",
    "label": 0
  },
  {
    "text": "除了隔音很差，其他都环境不错",
    "label": 1
  },
  {
    "text": "本来网络很慢，结果服务很好",
    "label": 1
  },
  {
    "text": "整体环境不错，就是设施陈旧",
    "label": 0
  },
  {
    "text": "虽然服务很好，但是价格太贵",
    "label": 0
  },
  {
    "text": "除了网络很慢，其他都房间干净",
    "label": 1
  },
  {
    "text": "价格太贵，不过性价比高",
    "label": 1
  },
  {
    "text": "位置便利，可惜价格太贵",
    "label": 0
  },
  {
    "text": "设施齐全，可惜网络很慢",
    "label": 0
  },
  {
    "text": "本来房间太小，结果环境不错",
    "label": 1
  },
  {
    "text": "隔音很差，不过服务很好",
    "label": 1
  },
  {
    "text": "除了价格太贵，其他都位置便利",
    "label": 1
  },
  {
    "text": "虽然服务很好，但是设施陈旧",
    "label": 0
  },
  {
    "text": "虽然环境不错，但是早餐难吃",
    "label": 0
  },
  {
    "text": "性价比高，可惜设施陈旧",
    "label": 0
  },
  {
    "text": "整体位置便利，就是网络很慢",
    "label": 0
  },
  {
    "text": "环境不错，可惜房间太小",
    "label": 0
  },
  {
    "text": "虽然性价比高，但是隔音很差",
    "label": 0
  },
  {
    "text": "整体性价比高，就是设施陈旧",
    "label": 0
  },
  {
    "text": "设施齐全，可惜房间太小",
    "label": 0
  },
  {
    "text": "设施齐全，可惜房间太小",
    "label": 0
  },
  {
    "text": "房间干净，可惜设施陈旧",
    "label": 0
  },
  {
    "text": "本来早餐难吃，结果性价比高",
    "label": 1
  },
  {
    "text": "除了房间太小，其他都环境不错",
    "label": 1
  },
  {
    "text": "虽然房间干净，但是隔音很差",
    "label": 0
  },
  {
    "text": "虽然环境不错，但是网络很慢",
    "label": 0
  },
  {
    "text": "隔音很差，不过房间干净",
    "label": 1
  },
  {
    "text": "位置便利，可惜隔音很差",
    "label": 0
  },
  {
    "text": "设施陈旧，不过性价比高",
    "label": 1
  },
  {
    "text": "价格太贵，不过房间干净",
    "label": 1
  },
  {
    "text": "房间干净，可惜设施陈旧",
    "label": 0
  },
  {
    "text": "除了设施陈旧，其他都性价比高",
    "label": 1
  },
  {
    "text": "设施齐全，可惜隔音很差",
    "label": 0
  },
  {
    "text": "早餐难吃，不过位置便利",
    "label": 1
  },
  {
    "text": "整体性价比高，就是设施陈旧",
    "label": 0
  },
  {
    "text": "性价比高，可惜网络很慢",
    "label": 0
  },
  {
    "text": "本来房间太小，结果性价比高",
    "label": 1
  },
  {
    "text": "除了设施陈旧，其他都设施齐全",
    "label": 1
  },
  {
    "text": "本来隔音很差，结果房间干净",
    "label": 1
  },
  {
    "text": "房间干净，可惜设施陈旧",
    "label": 0
  },
  {
    "text": "网络很慢，不过环境不错",
    "label": 1
  },
  {
    "text": "本来设施陈旧，结果服务很好",
    "label": 1
  },
  {
    "text": "虽然性价比高，但是隔音很差",
    "label": 0
  },
  {
    "text": "整体位置便利，就是早餐难吃",
    "label": 0
  },
  {
    "text": "虽然环境不错，但是早餐难吃",
    "label": 0
  },
  {
    "text": "整体服务很好，就是价格太贵",
    "label": 0
  },
  {
    "text": "整体性价比高，就是房间太小",
    "label": 0
  },
  {
    "text": "除了设施陈旧，其他都环境不错",
    "label": 1
  },
  {
    "text": "设施陈旧，不过设施齐全",
    "label": 1
  },
  {
    "text": "隔音很差，不过环境不错",
    "label": 1
  },
  {
    "text": "性价比高，可惜价格太贵",
    "label": 0
  },
  {
    "text": "整体房间干净，就是网络很慢",
    "label": 0
  },
  {
    "text": "虽然位置便利，但是价格太贵",
    "label": 0
  },
  {
    "text": "整体房间干净，就是设施陈旧",
    "label": 0
  },
  {
    "text": "虽然位置便利，但是房间太小",
    "label": 0
  },
  {
    "text": "本来网络很慢，结果环境不错",
    "label": 1
  },
  {
    "text": "性价比高，可惜隔音很差",
    "label": 0
  },
  {
    "text": "本来房间太小，结果服务很好",
    "label": 1
  },
  {
    "text": "整体设施齐全，就是隔音很差",
    "label": 0
  },
  {
    "text": "本来设施陈旧，结果设施齐全",
    "label": 1
  },
  {
    "text": "虽然性价比高，但是设施陈旧",
    "label": 0
  },
  {
    "text": "本来网络很慢，结果性价比高",
    "label": 1
  },
  {
    "text": "本来早餐难吃，结果服务很好",
    "label": 1
  },
  {
    "text": "设施齐全，可惜设施陈旧",
    "label": 0
  },
  {
    "text": "除了网络很慢，其他都性价比高",
    "label": 1
  },
  {
    "text": "虽然性价比高，但是设施陈旧",
    "label": 0
  },
  {
    "text": "除了设施陈旧，其他都性价比高",
    "label": 1
  },
  {
    "text": "网络很慢，不过位置便利",
    "label": 1
  },
  {
    "text": "虽然环境不错，但是网络很慢",
    "label": 0
  },
  {
    "text": "整体环境不错，就是设施陈旧",
    "label": 0
  },
  {
    "text": "除了早餐难吃，其他都环境不错",
    "label": 1
  },
  {
    "text": "早餐难吃，不过位置便利",
    "label": 1
  },
  {
    "text": "虽然环境不错，但是网络很慢",
    "label": 0
  },
  {
    "text": "虽然服务很好，但是房间太小",
    "label": 0
  },
  {
    "text": "整体服务很好，就是早餐难吃",
    "label": 0
  },
  {
    "text": "隔音很差，不过服务很好",
    "label": 1
  },
  {
    "text": "整体位置便利，就是房间太小",
    "label": 0
  },
  {
    "text": "本来隔音很差，结果房间干净",
    "label": 1
  },
  {
    "text": "房间太小，不过房间干净",
    "label": 1
  },
  {
    "text": "虽然房间干净，但是房间太小",
    "label": 0
  },
  {
    "text": "位置便利，可惜网络很慢",
    "label": 0
  },
  {
    "text": "整体位置便利，就是早餐难吃",
    "label": 0
  },
  {
    "text": "虽然设施齐全，但是网络很慢",
    "label": 0
  },
  {
    "text": "性价比高，可惜早餐难吃",
    "label": 0
  },
  {
    "text": "网络很慢，不过房间干净",
    "label": 1
  },
  {
    "text": "除了隔音很差，其他都位置便利",
    "label": 1
  },
  {
    "text": "虽然服务很好，但是设施陈旧",
    "label": 0
  },
  {
    "text": "隔音很差，不过房间干净",
    "label": 1
  },
  {
    "text": "虽然性价比高，但是房间太小",
    "label": 0
  },
  {
    "text": "价格太贵，不过性价比高",
    "label": 1
  },
  {
    "text": "除了早餐难吃，其他都房间干净",
    "label": 1
  },
  {
    "text": "整体房间干净，就是房间太小",
    "label": 0
  },
  {
    "text": "环境不错，可惜房间太小",
    "label": 0
  },
  {
    "text": "本来网络很慢，结果房间干净",
    "label": 1
  },
  {
    "text": "本来早餐难吃，结果位置便利",
    "label": 1
  },
  {
    "text": "总体还可以，就是有些小瑕疵",
    "label": 1
  },
  {
    "text": "基本满意，性价比尚可",
    "label": 1
  },
  {
    "text": "一般般，没什么特别的",
    "label": 0
  },
  {
    "text": "勉强能住，凑合一晚",
    "label": 0
  },
  {
    "text": "还行吧，下次可能不会再来",
    "label": 0
  },
  {
    "text": "中规中矩，符合预期",
    "label": 1
  },
  {
    "text": "尚可接受，但谈不上惊喜",
    "label": 0
  },
  {
    "text": "超出预期，相当不错",
    "label": 1
  },
  {
    "text": "差强人意，勉强及格",
    "label": 0
  },
  {
    "text": "物有所值，推荐入住",
    "label": 1
  },
  {
    "text": "性价比一般，不太推荐",
    "label": 0
  },
  {
    "text": "整体满意，会再次光顾",
    "label": 1
  },
  {
    "text": "体验平平，没有亮点",
    "label": 0
  },
  {
    "text": "相当满意，值得推荐",
    "label": 1
  },
  {
    "text": "略显失望，期望过高",
    "label": 0
  },
  {
    "text": "总体还可以，就是有些小瑕疵",
    "label": 1
  },
  {
    "text": "基本满意，性价比尚可",
    "label": 1
  },
  {
    "text": "一般般，没什么特别的",
    "label": 0
  },
  {
    "text": "勉强能住，凑合一晚",
    "label": 0
  },
  {
    "text": "还行吧，下次可能不会再来",
    "label": 0
  },
  {
    "text": "中规中矩，符合预期",
    "label": 1
  },
  {
    "text": "尚可接受，但谈不上惊喜",
    "label": 0
  },
  {
    "text": "超出预期，相当不错",
    "label": 1
  },
  {
    "text": "差强人意，勉强及格",
    "label": 0
  },
  {
    "text": "物有所值，推荐入住",
    "label": 1
  },
  {
    "text": "性价比一般，不太推荐",
    "label": 0
  },
  {
    "text": "整体满意，会再次光顾",
    "label": 1
  },
  {
    "text": "体验平平，没有亮点",
    "label": 0
  },
  {
    "text": "相当满意，值得推荐",
    "label": 1
  },
  {
    "text": "略显失望，期望过高",
    "label": 0
  },
  {
    "text": "总体还可以，就是有些小瑕疵",
    "label": 1
  },
  {
    "text": "基本满意，性价比尚可",
    "label": 1
  },
  {
    "text": "一般般，没什么特别的",
    "label": 0
  },
  {
    "text": "勉强能住，凑合一晚",
    "label": 0
  },
  {
    "text": "还行吧，下次可能不会再来",
    "label": 0
  },
  {
    "text": "中规中矩，符合预期",
    "label": 1
  },
  {
    "text": "尚可接受，但谈不上惊喜",
    "label": 0
  },
  {
    "text": "超出预期，相当不错",
    "label": 1
  },
  {
    "text": "差强人意，勉强及格",
    "label": 0
  },
  {
    "text": "物有所值，推荐入住",
    "label": 1
  },
  {
    "text": "性价比一般，不太推荐",
    "label": 0
  },
  {
    "text": "整体满意，会再次光顾",
    "label": 1
  },
  {
    "text": "体验平平，没有亮点",
    "label": 0
  },
  {
    "text": "相当满意，值得推荐",
    "label": 1
  },
  {
    "text": "略显失望，期望过高",
    "label": 0
  },
  {
    "text": "总体还可以，就是有些小瑕疵",
    "label": 1
  },
  {
    "text": "基本满意，性价比尚可",
    "label": 1
  },
  {
    "text": "一般般，没什么特别的",
    "label": 0
  },
  {
    "text": "勉强能住，凑合一晚",
    "label": 0
  },
  {
    "text": "还行吧，下次可能不会再来",
    "label": 0
  },
  {
    "text": "中规中矩，符合预期",
    "label": 1
  },
  {
    "text": "尚可接受，但谈不上惊喜",
    "label": 0
  },
  {
    "text": "超出预期，相当不错",
    "label": 1
  },
  {
    "text": "差强人意，勉强及格",
    "label": 0
  },
  {
    "text": "物有所值，推荐入住",
    "label": 1
  },
  {
    "text": "性价比一般，不太推荐",
    "label": 0
  },
  {
    "text": "整体满意，会再次光顾",
    "label": 1
  },
  {
    "text": "体验平平，没有亮点",
    "label": 0
  },
  {
    "text": "相当满意，值得推荐",
    "label": 1
  },
  {
    "text": "略显失望，期望过高",
    "label": 0
  },
  {
    "text": "总体还可以，就是有些小瑕疵",
    "label": 1
  },
  {
    "text": "基本满意，性价比尚可",
    "label": 1
  },
  {
    "text": "一般般，没什么特别的",
    "label": 0
  },
  {
    "text": "勉强能住，凑合一晚",
    "label": 0
  },
  {
    "text": "还行吧，下次可能不会再来",
    "label": 0
  },
  {
    "text": "中规中矩，符合预期",
    "label": 1
  },
  {
    "text": "尚可接受，但谈不上惊喜",
    "label": 0
  },
  {
    "text": "超出预期，相当不错",
    "label": 1
  },
  {
    "text": "差强人意，勉强及格",
    "label": 0
  },
  {
    "text": "物有所值，推荐入住",
    "label": 1
  },
  {
    "text": "性价比一般，不太推荐",
    "label": 0
  },
  {
    "text": "整体满意，会再次光顾",
    "label": 1
  },
  {
    "text": "体验平平，没有亮点",
    "label": 0
  },
  {
    "text": "相当满意，值得推荐",
    "label": 1
  },
  {
    "text": "略显失望，期望过高",
    "label": 0
  },
  {
    "text": "总体还可以，就是有些小瑕疵",
    "label": 1
  },
  {
    "text": "基本满意，性价比尚可",
    "label": 1
  },
  {
    "text": "一般般，没什么特别的",
    "label": 0
  },
  {
    "text": "勉强能住，凑合一晚",
    "label": 0
  },
  {
    "text": "还行吧，下次可能不会再来",
    "label": 0
  },
  {
    "text": "中规中矩，符合预期",
    "label": 1
  },
  {
    "text": "尚可接受，但谈不上惊喜",
    "label": 0
  },
  {
    "text": "超出预期，相当不错",
    "label": 1
  },
  {
    "text": "差强人意，勉强及格",
    "label": 0
  },
  {
    "text": "物有所值，推荐入住",
    "label": 1
  },
  {
    "text": "性价比一般，不太推荐",
    "label": 0
  },
  {
    "text": "整体满意，会再次光顾",
    "label": 1
  },
  {
    "text": "体验平平，没有亮点",
    "label": 0
  },
  {
    "text": "相当满意，值得推荐",
    "label": 1
  },
  {
    "text": "略显失望，期望过高",
    "label": 0
  },
  {
    "text": "总体还可以，就是有些小瑕疵",
    "label": 1
  },
  {
    "text": "基本满意，性价比尚可",
    "label": 1
  },
  {
    "text": "一般般，没什么特别的",
    "label": 0
  },
  {
    "text": "勉强能住，凑合一晚",
    "label": 0
  },
  {
    "text": "还行吧，下次可能不会再来",
    "label": 0
  },
  {
    "text": "中规中矩，符合预期",
    "label": 1
  },
  {
    "text": "尚可接受，但谈不上惊喜",
    "label": 0
  },
  {
    "text": "超出预期，相当不错",
    "label": 1
  },
  {
    "text": "差强人意，勉强及格",
    "label": 0
  },
  {
    "text": "物有所值，推荐入住",
    "label": 1
  }
]